ovos_gguf_solver/__init__.py
ovos_gguf_solver/version.py
ovos_solver_gguf_plugin-0.1.1a2.dist-info/METADATA
ovos_solver_gguf_plugin-0.1.1a2.dist-info/WHEEL
ovos_solver_gguf_plugin-0.1.1a2.dist-info/entry_points.txt
ovos_solver_gguf_plugin-0.1.1a2.dist-info/top_level.txt
ovos_solver_gguf_plugin-0.1.1a2.dist-info/zip-safe
ovos_solver_gguf_plugin-0.1.1a2.dist-info/RECORD
