Metadata-Version: 2.4
Name: ovos-solver-gguf-plugin
Version: 0.1.1a2
Summary: A question solver plugin for OVOS
Home-page: https://github.com/TigreGotico/ovos-solver-gguf-plugin
Author: jarbasai
Author-email: jarbasai@mailfence.com
License: MIT
Keywords: OVOS openvoiceos plugin utterance fallback query
Requires-Dist: ovos-plugin-manager
Requires-Dist: huggingface-hub
Requires-Dist: llama-cpp-python
Dynamic: author
Dynamic: author-email
Dynamic: description
Dynamic: description-content-type
Dynamic: home-page
Dynamic: keywords
Dynamic: license
Dynamic: requires-dist
Dynamic: summary
